[
  { "word": "banana", "hint": "Fruta amarela e doce" },
  { "word": "janela", "hint": "Parte da casa que deixa entrar luz e ar" },
  { "word": "pessoa", "hint": "Ser humano" },
  { "word": "carro", "hint": "Veículo com quatro rodas" },
  { "word": "cachorro", "hint": "Melhor amigo do homem" },
  { "word": "livro", "hint": "Objeto com páginas para leitura" },
  { "word": "escola", "hint": "Lugar para aprender" },
  { "word": "computador", "hint": "Máquina para processar dados" },
  { "word": "praia", "hint": "Lugar com areia e mar" },
  { "word": "floresta", "hint": "Área com muitas árvores" }
]
